_pykwl.cpython-37m-x86_64-linux-gnu.so
pykwl-0.0.19.dist-info/WHEEL
pykwl-0.0.19.dist-info/LICENSE
pykwl-0.0.19.dist-info/top_level.txt
pykwl-0.0.19.dist-info/RECORD
pykwl-0.0.19.dist-info/METADATA
pykwl/__init__.py
pykwl/__init__.pyi
pykwl.libs/libgcc_s-a3a07607.so.1
