Metadata-Version: 2.1
Name: pykwl
Version: 0.0.19
Summary: Weisfeiler-Leman library
Home-page: https://github.com/drexlerd/Weisfeiler-Leman
Author: Simon Stahlberg, Dominik Drexler
Author-email: simon.stahlberg@gmail.com,dominik.drexler@liu.se
License-File: LICENSE
Requires-Dist: cmake >=3.21
Provides-Extra: test
Requires-Dist: pytest ; extra == 'test'
